wave_simulator/__init__.py
wave_simulator/animation_utils.py
wave_simulator/boundary_conditions.py
wave_simulator/oned_simulator.py
wave_simulator/twod_simulator.py
wave_simulator-0.0.2.dist-info/METADATA
wave_simulator-0.0.2.dist-info/WHEEL
wave_simulator-0.0.2.dist-info/licenses/LICENSE
wave_simulator-0.0.2.dist-info/RECORD
