Metadata-Version: 2.4
Name: wave_simulator
Version: 0.0.2
Summary: wave simulator
Project-URL: Homepage, https://github.com/caoqiming/wave-simulator
Project-URL: Issues, https://github.com/caoqiming/wave-simulator/issues
Author-email: qiming <qcao@tcd.ie>
License-Expression: MIT
License-File: LICENSE
Classifier: Programming Language :: Python :: 3
Requires-Python: >=3.9
Requires-Dist: matplotlib>=3.10.6
Requires-Dist: numpy>=2.0.2
